pymodorino/__init__.py
pymodorino/oi.wav
pymodorino/pomodorino.png
pymodorino/pymodoro.py
pymodorino/utils.py
pymodorino-0.0.18.dist-info/LICENSE
pymodorino-0.0.18.dist-info/METADATA
pymodorino-0.0.18.dist-info/WHEEL
pymodorino-0.0.18.dist-info/entry_points.txt
pymodorino-0.0.18.dist-info/top_level.txt
pymodorino-0.0.18.dist-info/RECORD
