Metadata-Version: 2.1
Name: pymodorino
Version: 0.0.18
Summary: Very simple and cross-platform (hopefully) pomodoro timer script...
Home-page: https://github.com/DominickVale/Pymodorino
Author: Dominick Vale
Author-email: dominickveil@gmail.com
License: UNKNOWN
Keywords: pomodoro timer,pomodoro,timer
Platform: UNKNOWN
Classifier: Programming Language :: Python :: 3
Classifier: License :: OSI Approved :: MIT License
Classifier: Operating System :: OS Independent
Requires-Python: >=3.8.0
Requires-Dist: blessed
Requires-Dist: notify-py
